cellnotifier/__init__.py
cellnotifier/sound.py
cellnotifier-0.1.3.dist-info/METADATA
cellnotifier-0.1.3.dist-info/WHEEL
cellnotifier-0.1.3.dist-info/top_level.txt
cellnotifier-0.1.3.dist-info/RECORD
