Metadata-Version: 2.4
Name: cellnotifier
Version: 0.1.3
Summary: Notify when a cell or process finishes running
Author: Your Name
Author-email: your@email.com
Classifier: Programming Language :: Python :: 3
Classifier: Operating System :: OS Independent
Requires-Python: >=3.6
Dynamic: author
Dynamic: author-email
Dynamic: classifier
Dynamic: description-content-type
Dynamic: requires-python
Dynamic: summary
